osc_placement/__init__.py
osc_placement/http.py
osc_placement/plugin.py
osc_placement/version.py
osc_placement/resources/__init__.py
osc_placement/resources/aggregate.py
osc_placement/resources/allocation.py
osc_placement/resources/allocation_candidate.py
osc_placement/resources/common.py
osc_placement/resources/inventory.py
osc_placement/resources/resource_class.py
osc_placement/resources/resource_provider.py
osc_placement/resources/trait.py
osc_placement/resources/usage.py
osc_placement/tests/__init__.py
osc_placement/tests/functional/__init__.py
osc_placement/tests/functional/base.py
osc_placement/tests/functional/test_aggregate.py
osc_placement/tests/functional/test_allocation.py
osc_placement/tests/functional/test_allocation_candidate.py
osc_placement/tests/functional/test_inventory.py
osc_placement/tests/functional/test_plugin.py
osc_placement/tests/functional/test_resource_class.py
osc_placement/tests/functional/test_resource_provider.py
osc_placement/tests/functional/test_trait.py
osc_placement/tests/functional/test_usage.py
osc_placement/tests/unit/__init__.py
osc_placement/tests/unit/test_allocation.py
osc_placement/tests/unit/test_common.py
osc_placement/tests/unit/test_http.py
osc_placement/tests/unit/test_plugin.py
osc_placement/tests/unit/test_version.py
osc_placement-4.7.0.dist-info/AUTHORS
osc_placement-4.7.0.dist-info/LICENSE
osc_placement-4.7.0.dist-info/METADATA
osc_placement-4.7.0.dist-info/WHEEL
osc_placement-4.7.0.dist-info/entry_points.txt
osc_placement-4.7.0.dist-info/pbr.json
osc_placement-4.7.0.dist-info/top_level.txt
osc_placement-4.7.0.dist-info/RECORD
