Metadata-Version: 2.1
Name: osc-placement
Version: 4.7.0
Summary: OpenStackClient plugin for the Placement service
Home-page: https://docs.openstack.org/osc-placement/latest/
Author: OpenStack
Author-email: openstack-discuss@lists.openstack.org
Classifier: Environment :: OpenStack
Classifier: Intended Audience :: Information Technology
Classifier: Intended Audience :: System Administrators
Classifier: License :: OSI Approved :: Apache Software License
Classifier: Operating System :: POSIX :: Linux
Classifier: Programming Language :: Python
Classifier: Programming Language :: Python :: Implementation :: CPython
Classifier: Programming Language :: Python :: 3 :: Only
Classifier: Programming Language :: Python :: 3
Classifier: Programming Language :: Python :: 3.9
Classifier: Programming Language :: Python :: 3.10
Classifier: Programming Language :: Python :: 3.11
Classifier: Programming Language :: Python :: 3.12
Requires-Python: >=3.9
License-File: LICENSE
Requires-Dist: pbr>=2.0.0
Requires-Dist: keystoneauth1>=3.3.0
Requires-Dist: osc-lib>=1.2.0
Requires-Dist: oslo.utils>=3.37.0
